mastercardp2m/__init__.py
mastercardp2m/digitalaccountreferencenumber.py
mastercardp2m/digitalaccountreferencenumberretrieval.py
mastercardp2m/funding.py
mastercardp2m/fundingreversal.py
mastercardp2m/merchantrefund.py
mastercardp2m/merchantretrieval.py
mastercardp2m/merchanttransferfundingandpayment.py
mastercardp2m/merchanttransferpayment.py
mastercardp2m/resourceconfig.py
mastercardp2m/testpaymentnotification.py
mastercardp2m/testrefundnotification.py
mastercardp2m/transfernotification.py
mastercardp2m/transfernotificationregistration.py
mastercard_p2m-1.0.4.dist-info/LICENSE
mastercard_p2m-1.0.4.dist-info/METADATA
mastercard_p2m-1.0.4.dist-info/WHEEL
mastercard_p2m-1.0.4.dist-info/top_level.txt
mastercard_p2m-1.0.4.dist-info/RECORD
